odoo/addons/l10n_eu_product_adr/README.rst
odoo/addons/l10n_eu_product_adr/__init__.py
odoo/addons/l10n_eu_product_adr/__manifest__.py
odoo/addons/l10n_eu_product_adr/data/adr_class.xml
odoo/addons/l10n_eu_product_adr/data/adr_goods.xml
odoo/addons/l10n_eu_product_adr/data/adr_label.xml
odoo/addons/l10n_eu_product_adr/data/adr_packing_instruction.xml
odoo/addons/l10n_eu_product_adr/data/uom_uom.xml
odoo/addons/l10n_eu_product_adr/i18n/de.po
odoo/addons/l10n_eu_product_adr/i18n/es.po
odoo/addons/l10n_eu_product_adr/i18n/fr.po
odoo/addons/l10n_eu_product_adr/i18n/it.po
odoo/addons/l10n_eu_product_adr/i18n/l10n_eu_product_adr.pot
odoo/addons/l10n_eu_product_adr/i18n/nl.po
odoo/addons/l10n_eu_product_adr/models/__init__.py
odoo/addons/l10n_eu_product_adr/models/adr_class.py
odoo/addons/l10n_eu_product_adr/models/adr_goods.py
odoo/addons/l10n_eu_product_adr/models/adr_label.py
odoo/addons/l10n_eu_product_adr/models/adr_packing_instruction.py
odoo/addons/l10n_eu_product_adr/models/common.py
odoo/addons/l10n_eu_product_adr/models/product_product.py
odoo/addons/l10n_eu_product_adr/models/product_template.py
odoo/addons/l10n_eu_product_adr/models/stock_move.py
odoo/addons/l10n_eu_product_adr/models/stock_picking.py
odoo/addons/l10n_eu_product_adr/readme/CONFIGURE.md
odoo/addons/l10n_eu_product_adr/readme/CONTRIBUTORS.md
odoo/addons/l10n_eu_product_adr/readme/CREDITS.md
odoo/addons/l10n_eu_product_adr/readme/DESCRIPTION.md
odoo/addons/l10n_eu_product_adr/readme/HISTORY.md
odoo/addons/l10n_eu_product_adr/readme/ROADMAP.md
odoo/addons/l10n_eu_product_adr/scripts/import_adr_multilang_xlsx.py
odoo/addons/l10n_eu_product_adr/scripts/import_adr_translations.py
odoo/addons/l10n_eu_product_adr/security/ir.model.access.csv
odoo/addons/l10n_eu_product_adr/security/res_groups.xml
odoo/addons/l10n_eu_product_adr/static/description/icon.png
odoo/addons/l10n_eu_product_adr/static/description/index.html
odoo/addons/l10n_eu_product_adr/static/img/ADR_1.4.svg
odoo_addon_l10n_eu_product_adr-18.0.1.0.1.24.dist-info/METADATA
odoo_addon_l10n_eu_product_adr-18.0.1.0.1.24.dist-info/WHEEL
odoo_addon_l10n_eu_product_adr-18.0.1.0.1.24.dist-info/top_level.txt
odoo_addon_l10n_eu_product_adr-18.0.1.0.1.24.dist-info/RECORD
