Metadata-Version: 2.1
Name: odoo-addon-l10n_eu_product_adr
Version: 18.0.1.0.1.24
Requires-Python: >=3.10
Requires-Dist: odoo==18.0.*
Summary: Allows to set appropriate danger class and components
Home-page: https://github.com/OCA/community-data-files
License: AGPL-3
Author: Opener B.V., Camptocamp, Odoo Community Association (OCA)
Author-email: support@odoo-community.org
Classifier: Programming Language :: Python
Classifier: Framework :: Odoo
Classifier: Framework :: Odoo :: 18.0
Classifier: License :: OSI Approved :: GNU Affero General Public License v3
Classifier: Development Status :: 4 - Beta
